magic_utils/__init__.py
magic_utils/eventmanager.py
magic_utils-0.1.0.dist-info/LICENSE
magic_utils-0.1.0.dist-info/METADATA
magic_utils-0.1.0.dist-info/WHEEL
magic_utils-0.1.0.dist-info/RECORD
