Metadata-Version: 2.1
Name: magic_utils
Version: 0.1.0
Summary: Contains useful utilities classes and functions.
Home-page: https://github.com/MrCode200/magic_utils
License: MIT
Keywords: keyword1,keyword2
Author: MrCode200
Author-email: navidyaghmaei@example.com
Requires-Python: >=3.11,<4.0
Classifier: License :: OSI Approved :: MIT License
Classifier: Programming Language :: Python :: 3
Classifier: Programming Language :: Python :: 3.11
Classifier: Programming Language :: Python :: 3.12
Project-URL: Repository, https://github.com/MrCode200/magic_utils
